{
  "as_of": "2025-11-05",
  "portfolio_value": 7850.49,
  "day_change": -17.67,
  "day_change_pct": -0.22,
  "positions": [
    {
      "ticker": "ABR",
      "name": "صندوق بريق للاستثمار",
      "units": 8,
      "avg_price": 181.30,
      "last": 181.31,
      "market_value": 1451.25,
      "pnl": 5.42,
      "pnl_pct": 0.37,
      "type": "fund"
    },
    {
      "ticker": "BMM",
      "name": "صندوق بلتون مية مية",
      "units": 2608,
      "avg_price": 1.53,
      "last": 1.55,
      "market_value": 4016.66,
      "pnl": 10.11,
      "pnl_pct": 0.25,
      "type": "fund"
    },
    {
      "ticker": "BSB",
      "name": "صندوق بلتون سبائك",
      "units": 3,
      "avg_price": 152.09,
      "last": 145.00,
      "market_value": 434.49,
      "pnl": -21.79,
      "pnl_pct": -4.78,
      "type": "fund"
    },
    {
      "ticker": "COMI",
      "name": "البنك التجاري الدولي",
      "units": 11,
      "avg_price": 105.61,
      "last": 106.90,
      "market_value": 1175.90,
      "pnl": 14.18,
      "pnl_pct": 1.22,
      "type": "stock"
    },
    {
      "ticker": "FWRY",
      "name": "فوري لتكنولوجيا البنوك والمدفوعات",
      "units": 54,
      "avg_price": 14.20,
      "last": 14.30,
      "market_value": 772.20,
      "pnl": -25.59,
      "pnl_pct": -3.21,
      "type": "stock"
    }
  ]
}
